README.rst
setup.py
hg_api/__init__.py
hg_api/api.py
hg_api/utils.py
hg_api.egg-info/PKG-INFO
hg_api.egg-info/SOURCES.txt
hg_api.egg-info/dependency_links.txt
hg_api.egg-info/not-zip-safe
hg_api.egg-info/requires.txt
hg_api.egg-info/top_level.txt