Metadata-Version: 1.1
Name: hg-api
Version: 0.1.0
Summary: A simple api interact with mercurial
Home-page: https://bitbucket.org/yafeile/hg_api
Author: yafeile
Author-email: yafeile@sohu.com
License: UNKNOWN
Keywords: hg
Platform: UNKNOWN
Classifier: Programming Language :: Python
